test/__init__.py
test/api_test.py
textdrip/__init__.py
textdrip/api.py
TextdripApi-0.1.0.dist-info/METADATA
TextdripApi-0.1.0.dist-info/WHEEL
TextdripApi-0.1.0.dist-info/top_level.txt
TextdripApi-0.1.0.dist-info/RECORD
