Metadata-Version: 2.1
Name: TextdripApi
Version: 0.1.0
Summary: Textdrip Api library
Author: Me
